hermes/__init__.py
hermes/__main__.py
hermes/_shipping_client.py
hermes/client.py
hermes/constants.py
hermes/file_parser.py
hermes/cli/__init__.py
hermes/cli/files.py
hermes/cli/main.py
hermes/cli/ups.py
darbiadev_hermes-0.4.0.dist-info/LICENSE
darbiadev_hermes-0.4.0.dist-info/METADATA
darbiadev_hermes-0.4.0.dist-info/WHEEL
darbiadev_hermes-0.4.0.dist-info/entry_points.txt
darbiadev_hermes-0.4.0.dist-info/top_level.txt
darbiadev_hermes-0.4.0.dist-info/RECORD
