Metadata-Version: 2.1
Name: darbiadev-hermes
Version: 0.4.0
Summary: Shipping tooling
Author-email: Bradley Reynolds <bradley.reynolds@darbia.dev>
License: MIT
Project-URL: repository, https://github.com/darbiadev/hermes/
Project-URL: documentation, https://docs.darbia.dev/hermes/
Requires-Python: <3.13,>=3.12
License-File: LICENSE
Requires-Dist: annotated-types ==0.6.0
Requires-Dist: anyio ==4.0.0
Requires-Dist: certifi ==2023.7.22
Requires-Dist: click ==8.1.7
Requires-Dist: darbiadev-shipping[ups] ==0.5.1
Requires-Dist: darbiadev-shipping-types ==0.3.0
Requires-Dist: darbiadev-ups ==0.7.0
Requires-Dist: et-xmlfile ==1.1.0
Requires-Dist: h11 ==0.14.0
Requires-Dist: httpcore ==0.18.0
Requires-Dist: httpx ==0.25.0
Requires-Dist: idna ==3.4
Requires-Dist: numpy ==1.26.2
Requires-Dist: openpyxl ==3.1.2
Requires-Dist: pandas ==2.1.4
Requires-Dist: pydantic ==2.5.3
Requires-Dist: pydantic-core ==2.14.6
Requires-Dist: pydantic-settings ==2.1.0
Requires-Dist: python-dateutil ==2.8.2
Requires-Dist: python-dotenv ==1.0.0
Requires-Dist: pytz ==2023.3.post1
Requires-Dist: six ==1.16.0
Requires-Dist: sniffio ==1.3.0
Requires-Dist: typer ==0.9.0
Requires-Dist: typing-extensions ==4.9.0
Requires-Dist: tzdata ==2023.3
Provides-Extra: dev
Requires-Dist: build ==1.0.3 ; extra == 'dev'
Requires-Dist: cfgv ==3.4.0 ; extra == 'dev'
Requires-Dist: click ==8.1.7 ; extra == 'dev'
Requires-Dist: distlib ==0.3.8 ; extra == 'dev'
Requires-Dist: filelock ==3.13.1 ; extra == 'dev'
Requires-Dist: identify ==2.5.33 ; extra == 'dev'
Requires-Dist: mypy ==1.8.0 ; extra == 'dev'
Requires-Dist: mypy-extensions ==1.0.0 ; extra == 'dev'
Requires-Dist: nodeenv ==1.8.0 ; extra == 'dev'
Requires-Dist: numpy ==1.26.2 ; extra == 'dev'
Requires-Dist: packaging ==23.2 ; extra == 'dev'
Requires-Dist: pandas-stubs ==2.1.4.231227 ; extra == 'dev'
Requires-Dist: pip-tools ==7.3.0 ; extra == 'dev'
Requires-Dist: platformdirs ==4.1.0 ; extra == 'dev'
Requires-Dist: pre-commit ==3.6.0 ; extra == 'dev'
Requires-Dist: pyproject-hooks ==1.0.0 ; extra == 'dev'
Requires-Dist: pyyaml ==6.0.1 ; extra == 'dev'
Requires-Dist: ruff ==0.1.9 ; extra == 'dev'
Requires-Dist: types-pytz ==2023.3.1.1 ; extra == 'dev'
Requires-Dist: typing-extensions ==4.9.0 ; extra == 'dev'
Requires-Dist: virtualenv ==20.25.0 ; extra == 'dev'
Requires-Dist: wheel ==0.42.0 ; extra == 'dev'
Provides-Extra: docs
Requires-Dist: alabaster ==0.7.13 ; extra == 'docs'
Requires-Dist: anyascii ==0.3.2 ; extra == 'docs'
Requires-Dist: astroid ==3.0.2 ; extra == 'docs'
Requires-Dist: babel ==2.14.0 ; extra == 'docs'
Requires-Dist: beautifulsoup4 ==4.12.2 ; extra == 'docs'
Requires-Dist: certifi ==2023.7.22 ; extra == 'docs'
Requires-Dist: charset-normalizer ==3.3.2 ; extra == 'docs'
Requires-Dist: docutils ==0.20.1 ; extra == 'docs'
Requires-Dist: furo ==2023.9.10 ; extra == 'docs'
Requires-Dist: idna ==3.4 ; extra == 'docs'
Requires-Dist: imagesize ==1.4.1 ; extra == 'docs'
Requires-Dist: jinja2 ==3.1.2 ; extra == 'docs'
Requires-Dist: markupsafe ==2.1.3 ; extra == 'docs'
Requires-Dist: packaging ==23.2 ; extra == 'docs'
Requires-Dist: pygments ==2.17.2 ; extra == 'docs'
Requires-Dist: pyyaml ==6.0.1 ; extra == 'docs'
Requires-Dist: releases ==2.1.1 ; extra == 'docs'
Requires-Dist: requests ==2.31.0 ; extra == 'docs'
Requires-Dist: semantic-version ==2.6.0 ; extra == 'docs'
Requires-Dist: snowballstemmer ==2.2.0 ; extra == 'docs'
Requires-Dist: soupsieve ==2.5 ; extra == 'docs'
Requires-Dist: sphinx ==7.2.6 ; extra == 'docs'
Requires-Dist: sphinx-autoapi ==3.0.0 ; extra == 'docs'
Requires-Dist: sphinx-basic-ng ==1.0.0b2 ; extra == 'docs'
Requires-Dist: sphinxcontrib-applehelp ==1.0.7 ; extra == 'docs'
Requires-Dist: sphinxcontrib-devhelp ==1.0.5 ; extra == 'docs'
Requires-Dist: sphinxcontrib-htmlhelp ==2.0.4 ; extra == 'docs'
Requires-Dist: sphinxcontrib-jsmath ==1.0.1 ; extra == 'docs'
Requires-Dist: sphinxcontrib-qthelp ==1.0.6 ; extra == 'docs'
Requires-Dist: sphinxcontrib-serializinghtml ==1.1.9 ; extra == 'docs'
Requires-Dist: urllib3 ==2.1.0 ; extra == 'docs'
Provides-Extra: tests
Requires-Dist: iniconfig ==2.0.0 ; extra == 'tests'
Requires-Dist: packaging ==23.2 ; extra == 'tests'
Requires-Dist: pluggy ==1.3.0 ; extra == 'tests'
Requires-Dist: pytest ==7.4.3 ; extra == 'tests'
Requires-Dist: pytest-randomly ==3.15.0 ; extra == 'tests'
